{
  "project_info": {
    "project_number": "248862924449",
    "project_id": "quizzfly-ebeb1",
    "storage_bucket": "quizzfly-ebeb1.firebasestorage.app"
  },
  "client": [
    {
      "client_info": {
        "mobilesdk_app_id": "1:248862924449:android:623d0a7d6f1a980127dae0",
        "android_client_info": {
          "package_name": "com.example.quizzfly_application_flutter"
        }
      },
      "oauth_client": [
        {
          "client_id": "248862924449-ldusjqjmpqies3g6f230lbn23b5o53sp.apps.googleusercontent.com",
          "client_type": 1,
          "android_info": {
            "package_name": "com.example.quizzfly_application_flutter",
            "certificate_hash": "9f6fdc138459b837dc53501affaa15b26cbe4cc2"
          }
        },
        {
          "client_id": "248862924449-2sh1t3hb2kf50e1lot9fh32291ujtteq.apps.googleusercontent.com",
          "client_type": 3
        }
      ],
      "api_key": [
        {
          "current_key": "AIzaSyB3X0oYhnV3WOcfwaDvzOo-ZPF2XpvOH5E"
        }
      ],
      "services": {
        "appinvite_service": {
          "other_platform_oauth_client": [
            {
              "client_id": "248862924449-2sh1t3hb2kf50e1lot9fh32291ujtteq.apps.googleusercontent.com",
              "client_type": 3
            }
          ]
        }
      }
    }
  ],
  "configuration_version": "1"
}